{
  "updated_at": "2026-03-25T11:27:27Z",
  "article_count": 314,
  "methodology_url": "/metodologia",
  "disclaimer_pt": "Análise algorítmica do tom das notícias coletadas. Não representa pesquisa de opinião.",
  "disclaimer_en": "Algorithmic analysis of collected news tone. Does not represent opinion polling.",
  "by_topic": {
    "caiado": {
      "armas": 0.0,
      "corrupcao": 0.0636,
      "economia": 1.0,
      "eleicoes": 0.2978,
      "meio_ambiente": 1.0,
      "midia": 0.48,
      "politica_ext": 0.4,
      "previdencia": -0.2,
      "seguranca": 0.28
    },
    "eduardo-leite": {
      "corrupcao": 0.3667,
      "eleicoes": 0.125,
      "politica_ext": 0.2,
      "seguranca": 0.0
    },
    "flavio-bolsonaro": {
      "armas": 0.0,
      "corrupcao": -0.0424,
      "economia": -0.1,
      "eleicoes": -0.0529,
      "impostos": 0.125,
      "lgbtq": 0.3333,
      "meio_ambiente": 0.05,
      "midia": -0.204,
      "politica_ext": -0.0416,
      "previdencia": 0.4,
      "privatizacao": -0.1,
      "saude": -0.0786,
      "seguranca": 0.0273
    },
    "lula": {
      "aborto": -0.2333,
      "armas": 0.025,
      "corrupcao": -0.1882,
      "economia": 0.0194,
      "educacao": 0.2,
      "eleicoes": -0.0752,
      "impostos": 0.1212,
      "indigenas": 0.05,
      "lgbtq": 0.02,
      "meio_ambiente": 0.3412,
      "midia": -0.3426,
      "politica_ext": 0.0015,
      "previdencia": -0.26,
      "privatizacao": 0.1,
      "saude": -0.09,
      "seguranca": -0.0071
    },
    "ratinho-jr": {
      "eleicoes": -0.2
    },
    "tarcisio": {
      "armas": 0.2,
      "corrupcao": -0.1143,
      "economia": 0.0,
      "eleicoes": -0.1944,
      "impostos": -0.325,
      "lgbtq": 1.0,
      "meio_ambiente": 0.5,
      "midia": -0.3333,
      "politica_ext": -0.0727,
      "privatizacao": -0.2,
      "saude": 0.325,
      "seguranca": 0.0
    },
    "zema": {
      "corrupcao": 0.7,
      "economia": 0.0,
      "eleicoes": 0.4125,
      "impostos": 0.4,
      "politica_ext": 0.4714,
      "privatizacao": 0.4
    }
  },
  "by_source": {
    "caiado": {
      "institutional": 0.0,
      "international": 0.1,
      "magazine": 0.2889,
      "mainstream": 0.4933,
      "politics": 0.205
    },
    "eduardo-leite": {
      "international": 0.1,
      "magazine": 0.04,
      "mainstream": 0.3333,
      "politics": -0.0333
    },
    "flavio-bolsonaro": {
      "institutional": -0.05,
      "international": 0.0,
      "magazine": -0.0793,
      "mainstream": -0.1245,
      "politics": 0.0838
    },
    "lula": {
      "institutional": 0.1976,
      "international": -0.0278,
      "magazine": -0.0295,
      "mainstream": -0.0189,
      "politics": -0.0144
    },
    "ratinho-jr": {
      "mainstream": -0.2
    },
    "tarcisio": {
      "magazine": 0.1,
      "mainstream": -0.0905,
      "politics": 0.5
    },
    "zema": {
      "magazine": 0.2,
      "mainstream": 0.6667,
      "politics": 0.3
    }
  }
}
