{
  "generated_at": "2026-04-03T21:24:59Z",
  "window_start": "2026-03-27T21:24:59Z",
  "window_end": "2026-04-03T21:24:59Z",
  "article_count": 485,
  "summary_pt": "Resumo semanal: 485 artigos validados/curados. Tema com maior cobertura: eleicoes. Candidato mais citado: lula.",
  "summary_en": "Weekly briefing: 485 validated/curated articles. Most covered topic: eleicoes. Most mentioned candidate: lula.",
  "trending_topics": [
    {
      "topic": "eleicoes",
      "article_count": 375,
      "avg_prominence": 0.591
    },
    {
      "topic": "politica_externa",
      "article_count": 365,
      "avg_prominence": 0.5943
    },
    {
      "topic": "corrupcao",
      "article_count": 249,
      "avg_prominence": 0.5919
    },
    {
      "topic": "midia",
      "article_count": 168,
      "avg_prominence": 0.6052
    },
    {
      "topic": "economia",
      "article_count": 142,
      "avg_prominence": 0.6189
    },
    {
      "topic": "impostos",
      "article_count": 94,
      "avg_prominence": 0.6277
    },
    {
      "topic": "seguranca",
      "article_count": 60,
      "avg_prominence": 0.6064
    },
    {
      "topic": "educacao",
      "article_count": 48,
      "avg_prominence": 0.5656
    },
    {
      "topic": "meio_ambiente",
      "article_count": 30,
      "avg_prominence": 0.6017
    },
    {
      "topic": "saude",
      "article_count": 29,
      "avg_prominence": 0.5556
    }
  ],
  "candidate_highlights": [
    {
      "candidate_slug": "lula",
      "article_count": 274,
      "avg_prominence": 0.6148,
      "avg_sentiment": 0.0864,
      "trend": "rising"
    },
    {
      "candidate_slug": "flavio-bolsonaro",
      "article_count": 99,
      "avg_prominence": 0.6554,
      "avg_sentiment": 0.0023,
      "trend": "rising"
    },
    {
      "candidate_slug": "caiado",
      "article_count": 41,
      "avg_prominence": 0.6247,
      "avg_sentiment": 0.0458,
      "trend": "stable"
    },
    {
      "candidate_slug": "tarcisio",
      "article_count": 21,
      "avg_prominence": 0.6554,
      "avg_sentiment": 0.0333,
      "trend": "rising"
    },
    {
      "candidate_slug": "eduardo-leite",
      "article_count": 13,
      "avg_prominence": 0.591,
      "avg_sentiment": 0.0341,
      "trend": "falling"
    },
    {
      "candidate_slug": "zema",
      "article_count": 10,
      "avg_prominence": 0.5944,
      "avg_sentiment": 0.0243,
      "trend": "falling"
    },
    {
      "candidate_slug": "renan-santos",
      "article_count": 6,
      "avg_prominence": 0.5806,
      "avg_sentiment": 0.0361,
      "trend": "falling"
    },
    {
      "candidate_slug": "aldo-rebelo",
      "article_count": 6,
      "avg_prominence": 0.5949,
      "avg_sentiment": 0.0528,
      "trend": "falling"
    }
  ],
  "editor_quality_audit": {
    "history_entries_by_tier": {
      "editor": 485,
      "editor-chefe": 331
    },
    "history_entries_by_action": {
      "curated": 331,
      "validated": 485
    },
    "editor_changed_fields": {
      "summary_en": 485,
      "summary_pt": 485
    },
    "low_confidence_articles": 0,
    "possible_foca_misclassification": 227
  },
  "top_articles": [
    {
      "id": "657483636b3112eb",
      "title": "Atriz ironiza picanha de Lula: “O Diabo sempre usou comida”",
      "url": "https://www.poder360.com.br/poder-gente/atriz-ironiza-picanha-de-lula-o-diabo-sempre-usou-comida/",
      "source": "Poder360",
      "published_at": "2026-04-03T19:40:05Z",
      "prominence_score": 0.9302,
      "status": "curated"
    },
    {
      "id": "c481d9c9d61c61d3",
      "title": "Lula oficializa número 2 de Alckmin para comandar Ministério da Indústria",
      "url": "https://www1.folha.uol.com.br/mercado/2026/04/lula-oficializa-numero-2-de-alckmin-para-comandar-ministerio-da-industria.shtml",
      "source": "UOL Noticias",
      "published_at": "2026-04-03T20:40:29Z",
      "prominence_score": 0.9227,
      "status": "curated"
    },
    {
      "id": "2446b5477d7c5d4d",
      "title": "A batalha de Minas: por que Lula aposta tudo em Pacheco",
      "url": "https://veja.abril.com.br/politica/a-batalha-de-minas-por-que-lula-aposta-tudo-em-pacheco/",
      "source": "Veja",
      "published_at": "2026-04-03T19:00:33Z",
      "prominence_score": 0.9086,
      "status": "curated"
    },
    {
      "id": "c4364d41c60da68c",
      "title": "Bancada evangélica mais alinhada a bolsonarismo ajuda Flávio e desafia Lula",
      "url": "https://noticias.uol.com.br/politica/ultimas-noticias/2026/04/03/bancada-evangelica-mais-alinhada-a-bolsonarismo-ajuda-flavio-e-desafia-lula.htm",
      "source": "UOL Noticias",
      "published_at": "2026-04-03T16:45:48Z",
      "prominence_score": 0.8894,
      "status": "curated"
    },
    {
      "id": "8e24ee78a5ae40b5",
      "title": "Graeml ingressa no PSD de Ratinho Jr. e mantém apoio a Flávio",
      "url": "https://oantagonista.com.br/brasil/graeml-ingressa-no-psd-de-ratinho-jr-e-mantem-apoio-a-flavio/",
      "source": "O Antagonista",
      "published_at": "2026-04-03T18:36:32Z",
      "prominence_score": 0.8892,
      "status": "curated"
    },
    {
      "id": "99a3b765dddb7554",
      "title": "Planalto oficializa exonerações de Geraldo Alckmin e Gleisi Hoffmann",
      "url": "https://www.redetv.uol.com.br/jornalismo/politica/planalto-oficializa-exoneracoes-de-geraldo-alckmin-e-gleisi-hoffmann",
      "source": "UOL Noticias",
      "published_at": "2026-04-03T19:03:55Z",
      "prominence_score": 0.8825,
      "status": "curated"
    },
    {
      "id": "9361323496765575",
      "title": "PT discute plano B para 2026 e admite risco de Lula ficar fora da disputa",
      "url": "https://veja.abril.com.br/politica/pt-discute-plano-b-para-2026-e-admite-risco-de-lula-ficar-fora-da-disputa/",
      "source": "Veja",
      "published_at": "2026-04-03T18:00:22Z",
      "prominence_score": 0.8781,
      "status": "curated"
    },
    {
      "id": "d29d098122f72474",
      "title": "Integrantes do PL que se omitem traem Bolsonaro, diz Carlos",
      "url": "https://www.poder360.com.br/poder-eleicoes/integrantes-do-pl-que-se-omitem-traem-bolsonaro-diz-carlos/",
      "source": "Poder360",
      "published_at": "2026-04-03T14:28:27Z",
      "prominence_score": 0.8768,
      "status": "curated"
    },
    {
      "id": "95bb1ddbf5e75131",
      "title": "Meio-Dia em Brasília: Projeções com o fim da janela partidária",
      "url": "https://oantagonista.com.br/videos/meio-dia-em-brasilia-projecoes-com-o-fim-da-janela-partidaria/",
      "source": "O Antagonista",
      "published_at": "2026-04-03T14:40:57Z",
      "prominence_score": 0.8757,
      "status": "curated"
    },
    {
      "id": "36d1bb1099d849f2",
      "title": "Flávio Bolsonaro nega que vai acabar com Pix se for eleito",
      "url": "https://www.poder360.com.br/poder-eleicoes/flavio-bolsonaro-nega-que-vai-acabar-com-pix-se-for-eleito/",
      "source": "Poder360",
      "published_at": "2026-04-03T14:13:06Z",
      "prominence_score": 0.8744,
      "status": "curated"
    }
  ]
}
