{
  "updated_at": "2026-03-20T17:53:12Z",
  "article_count": 420,
  "methodology_url": "/metodologia",
  "disclaimer_pt": "Análise algorítmica do tom das notícias coletadas. Não representa pesquisa de opinião.",
  "disclaimer_en": "Algorithmic analysis of collected news tone. Does not represent opinion polling.",
  "by_topic": {
    "aldo-rebelo": {
      "eleicoes": -0.025
    },
    "caiado": {
      "corrupcao": 0.3667,
      "economia": 0.764,
      "educacao": 0.284,
      "eleicoes": 0.2673,
      "impostos": 0.3,
      "indigenas": 0.3,
      "lgbtq": 0.3,
      "meio_ambiente": 0.7167,
      "midia": 0.3222,
      "politica_ext": 0.4188,
      "saude": 0.63,
      "seguranca": 0.4733
    },
    "eduardo-leite": {
      "corrupcao": 1.0,
      "educacao": 1.0,
      "eleicoes": 0.3167,
      "politica_ext": 1.0
    },
    "flavio-bolsonaro": {
      "corrupcao": -0.092,
      "economia": 0.3364,
      "educacao": 1.0,
      "eleicoes": -0.0,
      "impostos": 0.3,
      "indigenas": 0.45,
      "lgbtq": -0.3273,
      "meio_ambiente": 0.3333,
      "midia": -0.3231,
      "politica_ext": -0.0156,
      "previdencia": 0.15,
      "privatizacao": 0.0,
      "saude": 0.1133,
      "seguranca": 0.05
    },
    "lula": {
      "armas": 0.2333,
      "corrupcao": -0.1294,
      "economia": 0.04,
      "educacao": 0.39,
      "eleicoes": 0.066,
      "impostos": -0.0062,
      "indigenas": 0.4,
      "lgbtq": 0.1333,
      "meio_ambiente": 0.2355,
      "midia": 0.0299,
      "politica_ext": 0.0266,
      "previdencia": -0.1182,
      "privatizacao": -0.1667,
      "saude": 0.175,
      "seguranca": 0.0717
    },
    "ratinho-jr": {
      "eleicoes": 0.1,
      "midia": 0.1,
      "politica_ext": 0.1
    },
    "renan-santos": {
      "corrupcao": 0.0,
      "eleicoes": -0.0125,
      "midia": 0.1,
      "politica_ext": 0.0
    },
    "tarcisio": {
      "corrupcao": -0.0154,
      "economia": -0.3684,
      "educacao": 0.1,
      "eleicoes": -0.1771,
      "impostos": -0.2313,
      "indigenas": -1.0,
      "meio_ambiente": -0.5429,
      "midia": -0.28,
      "politica_ext": -0.0897,
      "privatizacao": -0.3375,
      "saude": 0.05,
      "seguranca": -0.06
    },
    "zema": {
      "corrupcao": -0.6167,
      "economia": 0.6,
      "educacao": 0.6,
      "eleicoes": -0.1107,
      "midia": -0.65,
      "politica_ext": 0.0556,
      "privatizacao": 1.0
    }
  },
  "by_source": {
    "aldo-rebelo": {
      "magazine": -0.05,
      "politics": 0.0
    },
    "caiado": {
      "institutional": 0.15,
      "international": 0.3,
      "magazine": 0.1643,
      "mainstream": 0.3286,
      "party": 0.2,
      "politics": 0.4092
    },
    "eduardo-leite": {
      "magazine": -0.05,
      "mainstream": 1.0,
      "politics": 0.0
    },
    "flavio-bolsonaro": {
      "institutional": -0.15,
      "international": -0.1,
      "magazine": 0.0128,
      "mainstream": 0.0193,
      "politics": 0.0258
    },
    "lula": {
      "institutional": 0.1154,
      "international": 0.1,
      "magazine": 0.0506,
      "mainstream": -0.0431,
      "party": -0.1,
      "politics": 0.1264
    },
    "ratinho-jr": {
      "mainstream": 0.1
    },
    "renan-santos": {
      "magazine": -0.05,
      "politics": 0.0
    },
    "tarcisio": {
      "magazine": -0.1812,
      "mainstream": -0.1448,
      "politics": -0.0625
    },
    "zema": {
      "magazine": -0.05,
      "mainstream": 0.0,
      "politics": -0.1
    }
  }
}
